MANIFEST.in
README.md
setup.py
src/fake/__init__.py
src/fake/data/__init__.py
src/fake/data/cities.json
src/fake/data/companies.json
src/fake/data/countries.json
src/fake/data/domains.json
src/fake/data/firstnames-female.json
src/fake/data/firstnames-male.json
src/fake/data/lastnames.json
src/fake/data/streets.json
src/fake/data/users.json
src/fake/data/words.json
src/fake_data.egg-info/PKG-INFO
src/fake_data.egg-info/SOURCES.txt
src/fake_data.egg-info/dependency_links.txt
src/fake_data.egg-info/top_level.txt