Metadata-Version: 1.1
Name: fake-data
Version: 0.9.1
Summary: Deterministic fake data generator
Home-page: http://github.com/sebastien/fake
Author: Sébastien Pierre
Author-email: sebastien.pierre@gmail.com
License: License :: OSI Approved :: BSD License
Download-URL: https://github.com/sebastien/fake/tarball/0.9.1
Keywords: fake,data,generator
Platform: UNKNOWN
Classifier: Programming Language :: Python
Classifier: Topic :: Utilities
Classifier: Development Status :: 4 - Beta
Classifier: Environment :: Console
Classifier: Intended Audience :: Developers
Classifier: License :: OSI Approved :: BSD License
Classifier: Natural Language :: English
Classifier: Topic :: Utilities
Classifier: Operating System :: POSIX
Classifier: Programming Language :: Python
